vedro_lazy_rerunner/__init__.py
vedro_lazy_rerunner/_rerunner.py
vedro_lazy_rerunner/_scheduler.py
vedro_lazy_rerunner-0.1.1.dist-info/LICENSE
vedro_lazy_rerunner-0.1.1.dist-info/METADATA
vedro_lazy_rerunner-0.1.1.dist-info/WHEEL
vedro_lazy_rerunner-0.1.1.dist-info/top_level.txt
vedro_lazy_rerunner-0.1.1.dist-info/RECORD
