Metadata-Version: 2.1
Name: vedro-lazy-rerunner
Version: 0.1.1
Summary: Rerunner plugin for the Vedro testing framework
Home-page: https://github.com/kvs8/vedro-lazy-rerunner
Author: Konstantin Shefer
Author-email: kostya.shefer.999@gmail.com
License: Apache-2.0
Classifier: License :: OSI Approved :: Apache Software License
Classifier: Programming Language :: Python :: 3.8
Classifier: Programming Language :: Python :: 3.9
Classifier: Programming Language :: Python :: 3.10
Classifier: Programming Language :: Python :: 3.11
Requires-Python: >=3.8
License-File: LICENSE
Requires-Dist: vedro <2.0,>=1.10
